__init__.py
orientLoss.py
orientloss-0.0.8.dist-info/licenses/LICENSE
orientloss-0.0.8.dist-info/METADATA
orientloss-0.0.8.dist-info/WHEEL
orientloss-0.0.8.dist-info/top_level.txt
orientloss-0.0.8.dist-info/RECORD
