Metadata-Version: 2.4
Name: orientLoss
Version: 0.0.8
Summary: orientLoss is a classification loss function @pytorch. It less prone to overfitting compared to crossEntropy. Compatible with random vector/embeddings with direction-indicating categories、probabilistic、oneHot as target. 
Author-email: Psyche Halo <Psyche@WinsGod.com>
Project-URL: Homepage, https://github.com/PsycheHalo/orientLoss
Project-URL: Issues, https://github.com/PsycheHalo/orientLoss/issues
Keywords: orientLoss,Loss,PyTorch,AI,neural,NN,classification,categories
Classifier: Programming Language :: Python :: 3
Classifier: Operating System :: OS Independent
Requires-Python: >=3.8
License-File: LICENSE
Requires-Dist: torch>=1.7.0
Dynamic: license-file
